excalibur/__init__.py
excalibur/__main__.py
excalibur/__version__.py
excalibur/cli.py
excalibur/configuration.py
excalibur/models.py
excalibur/settings.py
excalibur/tasks.py
excalibur/config_templates/__init__.py
excalibur/config_templates/default_celery.py
excalibur/config_templates/default_excalibur.cfg
excalibur/executors/__init__.py
excalibur/executors/base_executor.py
excalibur/executors/celery_executor.py
excalibur/executors/sequential_executor.py
excalibur/operators/__init__.py
excalibur/operators/base_operator.py
excalibur/operators/python_operator.py
excalibur/utils/__init__.py
excalibur/utils/database.py
excalibur/utils/file.py
excalibur/utils/metadata.py
excalibur/utils/module_loading.py
excalibur/utils/task.py
excalibur/www/__init__.py
excalibur/www/app.py
excalibur/www/views.py
excalibur/www/static/favicon.ico
excalibur/www/static/css/base.css
excalibur/www/static/css/workspace.css
excalibur/www/static/css/images/bt-delete-bak.png
excalibur/www/static/css/images/bt-delete.png
excalibur/www/static/css/images/outline.gif
excalibur/www/static/css/vendor/bootstrap.min.css
excalibur/www/static/css/vendor/fontawesome.css
excalibur/www/static/css/vendor/jquery-ui.min.css
excalibur/www/static/css/vendor/jquery-ui.structure.min.css
excalibur/www/static/css/vendor/jquery-ui.theme.min.css
excalibur/www/static/css/vendor/jquery.selectareas.css
excalibur/www/static/css/webfonts/fa-brands-400.eot
excalibur/www/static/css/webfonts/fa-brands-400.svg
excalibur/www/static/css/webfonts/fa-brands-400.ttf
excalibur/www/static/css/webfonts/fa-brands-400.woff
excalibur/www/static/css/webfonts/fa-brands-400.woff2
excalibur/www/static/css/webfonts/fa-regular-400.eot
excalibur/www/static/css/webfonts/fa-regular-400.svg
excalibur/www/static/css/webfonts/fa-regular-400.ttf
excalibur/www/static/css/webfonts/fa-regular-400.woff
excalibur/www/static/css/webfonts/fa-regular-400.woff2
excalibur/www/static/css/webfonts/fa-solid-900.eot
excalibur/www/static/css/webfonts/fa-solid-900.svg
excalibur_py-1.0.1.dist-info/AUTHORS.md
excalibur_py-1.0.1.dist-info/LICENSE
excalibur_py-1.0.1.dist-info/METADATA
excalibur_py-1.0.1.dist-info/WHEEL
excalibur_py-1.0.1.dist-info/entry_points.txt
excalibur_py-1.0.1.dist-info/top_level.txt
excalibur_py-1.0.1.dist-info/RECORD
