Metadata-Version: 2.1
Name: excalibur-py
Version: 1.0.1
Summary: A web interface to extract tabular data from PDFs
Author-email: Vinayak Mehta <vmehta94@gmail.com>
License: MIT
Project-URL: Homepage, https://github.com/camelot-dev/excalibur
Project-URL: Repository, https://github.com/camelot-dev/excalibur
Project-URL: Documentation, https://excalibur-py.readthedocs.io/
Project-URL: Changelog, https://github.com/camelot-dev/excalibur/releases
Classifier: Programming Language :: Python :: 3.9
Classifier: Programming Language :: Python :: 3.10
Classifier: Programming Language :: Python :: 3.11
Classifier: Programming Language :: Python :: 3.12
Classifier: Programming Language :: Python :: 3.13
Classifier: License :: OSI Approved :: MIT License
Requires-Python: >=3.9
License-File: LICENSE
License-File: AUTHORS.md
Requires-Dist: camelot-py>=1.0.0
Requires-Dist: celery>=4.1.1
Requires-Dist: click>=8.0.1
Requires-Dist: configparser>=7.1.0
Requires-Dist: Flask>=3.1.0
Requires-Dist: SQLAlchemy>=1.2.12
Requires-Dist: Werkzeug>=3.1.3
Requires-Dist: pypdfium2>=4
Requires-Dist: Pillow>=11.1.0
Provides-Extra: dev
Requires-Dist: pytest>=3.8.0; extra == "dev"
Requires-Dist: pytest-cov>=6.0.0; extra == "dev"
Requires-Dist: pytest-runner>=6.0.1; extra == "dev"
Requires-Dist: sphinx>=4.3.2; extra == "dev"
